LICENSE
MANIFEST.in
README.md
setup.py
geonode_worldmap/__init__.py
geonode_worldmap/context_processors.py
geonode_worldmap/hooksets.py
geonode_worldmap.egg-info/PKG-INFO
geonode_worldmap.egg-info/SOURCES.txt
geonode_worldmap.egg-info/dependency_links.txt
geonode_worldmap.egg-info/requires.txt
geonode_worldmap.egg-info/top_level.txt
geonode_worldmap/gazetteer/__init__.py
geonode_worldmap/gazetteer/admin.py
geonode_worldmap/gazetteer/flexidates.py
geonode_worldmap/gazetteer/models.py
geonode_worldmap/gazetteer/tests.py
geonode_worldmap/gazetteer/urls.py
geonode_worldmap/gazetteer/utils.py
geonode_worldmap/gazetteer/views.py
geonode_worldmap/gazetteer/management/__init__.py
geonode_worldmap/gazetteer/management/commands/__init__.py
geonode_worldmap/gazetteer/management/commands/updategazetteer.py
geonode_worldmap/gazetteer/migrations/0001_initial.py
geonode_worldmap/gazetteer/migrations/0002_gazetteerattribute.py
geonode_worldmap/gazetteer/migrations/0003_auto_20180316_1109.py
geonode_worldmap/gazetteer/migrations/__init__.py
geonode_worldmap/mapnotes/__init__.py
geonode_worldmap/mapnotes/admin.py
geonode_worldmap/mapnotes/models.py
geonode_worldmap/mapnotes/tests.py
geonode_worldmap/mapnotes/urls.py
geonode_worldmap/mapnotes/views.py
geonode_worldmap/mapnotes/migrations/0001_initial.py
geonode_worldmap/mapnotes/migrations/__init__.py
geonode_worldmap/templates/gazetteer/edit_layer_gazetteer.html
geonode_worldmap/templates/mapnotes/annotation.html
geonode_worldmap/templates/wm_extra/endpoint_add.html
geonode_worldmap/templates/wm_extra/endpoint_added.html
geonode_worldmap/templates/wm_extra/layers/edit_searchable_fields.html
geonode_worldmap/templates/wm_extra/maps/fullscreen.html
geonode_worldmap/templates/wm_extra/maps/map_detail.html
geonode_worldmap/templates/wm_extra/maps/map_include.html
geonode_worldmap/templates/wm_extra/maps/map_new.html
geonode_worldmap/templates/wm_extra/maps/map_print.html
geonode_worldmap/templates/wm_extra/maps/map_view.html
geonode_worldmap/templates/wm_extra/maps/mobile.html
geonode_worldmap/templates/wm_extra/maps/mobilemap.html
geonode_worldmap/templates/wm_extra/maps/mobile/app_header.html
