Metadata-Version: 1.0
Name: geonode-worldmap
Version: 0.2
Summary: GeoNode WorldMap applications
Home-page: http://geonode.org
Author: GeoNode Developers
Author-email: dev@geonode.org
License: GPL
Platform: UNKNOWN
